litequant/LSClient.cp38-win_amd64.pyd
litequant/LSClient.py
litequant/ParquetManager.cp38-win_amd64.pyd
litequant/ParquetManager.py
litequant/__init__.py
litequant-0.1.1.dist-info/METADATA
litequant-0.1.1.dist-info/WHEEL
litequant-0.1.1.dist-info/top_level.txt
litequant-0.1.1.dist-info/RECORD
